optify-0.8.2.dist-info/METADATA
optify-0.8.2.dist-info/WHEEL
optify-0.8.2.dist-info/licenses/LICENSE.txt
optify/__init__.py
optify/optify.cp313-win_amd64.pyd
optify/optify.pyi
optify/py.typed
optify-0.8.2.dist-info/RECORD
