Metadata-Version: 2.4
Name: optify
Version: 0.8.2
Classifier: Programming Language :: Rust
Classifier: Programming Language :: Python :: Implementation :: CPython
Classifier: Programming Language :: Python :: Implementation :: PyPy
Requires-Dist: pytest ; extra == 'dev'
Provides-Extra: dev
License-File: LICENSE.txt
Summary: Simplifies getting the right configuration options for a process using pre-loaded configurations from files to manage options for experiments or flights.
Home-Page: https://github.com/juharris/optify/tree/main/rust/optify
Author: Justin D. Harris
License-Expression: MIT
Requires-Python: >=3.8
Project-URL: Homepage, https://github.com/juharris/optify
Project-URL: Issues, https://github.com/juharris/optify/issues
